CHANGES.txt
MANIFEST.in
README.txt
TODO.txt
VERSION.txt
setup.cfg
setup.py
Khan.egg-info/PKG-INFO
Khan.egg-info/SOURCES.txt
Khan.egg-info/dependency_links.txt
Khan.egg-info/entry_points.txt
Khan.egg-info/namespace_packages.txt
Khan.egg-info/not-zip-safe
Khan.egg-info/requires.txt
Khan.egg-info/top_level.txt
docs/Makefile
docs/build/doctrees/configure.doctree
docs/build/doctrees/environment.pickle
docs/build/doctrees/index.doctree
docs/build/doctrees/convention/changelog.doctree
docs/build/doctrees/deploy/django.doctree
docs/build/doctrees/deploy/webpy.doctree
docs/build/doctrees/modules/cache.doctree
docs/build/doctrees/modules/command.doctree
docs/build/doctrees/modules/compress.doctree
docs/build/doctrees/modules/controller.doctree
docs/build/doctrees/modules/error_document.doctree
docs/build/doctrees/modules/httpstatus.doctree
docs/build/doctrees/modules/json.doctree
docs/build/doctrees/modules/notification.doctree
docs/build/doctrees/modules/proxy.doctree
docs/build/doctrees/modules/schema.doctree
docs/build/doctrees/modules/security.doctree
docs/build/doctrees/modules/session.doctree
docs/build/doctrees/modules/static.doctree
docs/build/doctrees/modules/store.doctree
docs/build/doctrees/modules/urlparse.doctree
docs/build/doctrees/modules/virtualhost.doctree
docs/build/doctrees/modules/utils/decorator.doctree
docs/build/doctrees/modules/utils/encryption.doctree
docs/build/doctrees/modules/utils/functional.doctree
docs/build/doctrees/modules/utils/i18n.doctree
docs/build/doctrees/modules/utils/index.doctree
docs/build/doctrees/modules/utils/mapping.doctree
docs/build/doctrees/modules/utils/request_checks.doctree
docs/build/doctrees/modules/utils/testing.doctree
docs/build/doctrees/modules/utils/util.doctree
docs/source/conf.py
docs/source/configure.rst
docs/source/index.rst
docs/source/.static/.hidden
docs/source/convention/changelog.rst
docs/source/deploy/django.rst
docs/source/deploy/webpy.rst
docs/source/modules/cache.rst
docs/source/modules/command.rst
docs/source/modules/compress.rst
docs/source/modules/controller.rst
docs/source/modules/error_document.rst
docs/source/modules/httpstatus.rst
docs/source/modules/json.rst
docs/source/modules/notification.rst
docs/source/modules/proxy.rst
