Metadata-Version: 1.0
Name: Khan
Version: 0.1.3dev
Summary: 一个易于使用和部署的 WSGI 工具集
Home-page: http://bitbucket.org/khan/khan
Author: timbaby2008
Author-email: timbaby2008@gmail.com
License: UNKNOWN
Keywords: web wsgi khan framework
Platform: UNKNOWN
Classifier: Development Status :: 3 - Alpha
Classifier: Intended Audience :: Developers
Classifier: Programming Language :: Python
Classifier: Topic :: Internet :: WWW/HTTP
Classifier: Topic :: Internet :: WWW/HTTP :: Dynamic Content
Classifier: Topic :: Internet :: WWW/HTTP :: WSGI
Classifier: Topic :: Internet :: WWW/HTTP :: WSGI :: Application
